boorusync/__init__.py
boorusync/__main__.py
boorusync/core/__init__.py
boorusync/core/config.py
boorusync/core/network.py
boorusync/core/boards/danbooru.py
boorusync-0.0.1.dist-info/licenses/LICENSE
tests/test_danbooru.py
tests/test_network.py
boorusync-0.0.1.dist-info/METADATA
boorusync-0.0.1.dist-info/WHEEL
boorusync-0.0.1.dist-info/entry_points.txt
boorusync-0.0.1.dist-info/top_level.txt
boorusync-0.0.1.dist-info/RECORD
