Metadata-Version: 2.4
Name: boorusync
Version: 0.0.1
Summary: Sync (and automatically download) your favorites between danbooru & gelbooru
Author-email: nichind <nichinddev@gmail.com>
License: MIT
Project-URL: Homepage, https://github.com/nichind/booru-sync
Project-URL: Issues, https://github.com/nichind/booru-sync/issues
Keywords: danbooru,gelbooru,sync,favorites,download,api,booru,cobalt
Classifier: Programming Language :: Python :: 3.11
Classifier: License :: OSI Approved :: MIT License
Classifier: Operating System :: OS Independent
Requires-Python: >=3.11
License-File: LICENSE
Dynamic: license-file
